santolabs/logging/fastapi/__init__.py
santolabs/logging/fastapi/logging.py
santolabs/logging/fastapi/package.py
santolabs/logging/fastapi/version.py
santolabs_logging_fastapi-0.0.2.dist-info/LICENSE
santolabs_logging_fastapi-0.0.2.dist-info/METADATA
santolabs_logging_fastapi-0.0.2.dist-info/WHEEL
santolabs_logging_fastapi-0.0.2.dist-info/entry_points.txt
santolabs_logging_fastapi-0.0.2.dist-info/top_level.txt
santolabs_logging_fastapi-0.0.2.dist-info/RECORD
